pyglet_ffmpeg2/__init__.py
pyglet_ffmpeg2/loader.py
pyglet_ffmpeg_two-0.1.17.dist-info/LICENSE
pyglet_ffmpeg_two-0.1.17.dist-info/METADATA
pyglet_ffmpeg_two-0.1.17.dist-info/NOTICE.txt
pyglet_ffmpeg_two-0.1.17.dist-info/WHEEL
pyglet_ffmpeg_two-0.1.17.dist-info/top_level.txt
pyglet_ffmpeg_two-0.1.17.dist-info/RECORD
